active_period_method/__init__.py
active_period_method/active_period_method.py
active_period_method/detect_bottlenecks.py
active_period_method/machine.py
active_period_method/utils/__init__.py
active_period_method/utils/data_generator.py
active_period_method/utils/natural_key.py
active_period_method-0.9.0.dist-info/licenses/LICENSE.txt
active_period_method-0.9.0.dist-info/METADATA
active_period_method-0.9.0.dist-info/WHEEL
active_period_method-0.9.0.dist-info/top_level.txt
active_period_method-0.9.0.dist-info/RECORD
