Metadata-Version: 2.4
Name: active_period_method
Version: 0.9.0
Summary: Bottleneck detection via the active period method
Author-email: Martin Jestädt <m.jestaedt@ifakt.de>, Marco Bernreuther <marco.bernreuther@ipa.fraunhofer.de>, Benjamin Epple <b.epple@ifakt.de>
Project-URL: Homepage, https://gitlab.cc-asp.fraunhofer.de/mcb/active-period-method
Project-URL: Issues, https://gitlab.cc-asp.fraunhofer.de/mcb/active-period-method/-/issues
Classifier: Programming Language :: Python :: 3
Requires-Python: >=3.10
License-File: LICENSE.txt
Requires-Dist: matplotlib~=3.10
Requires-Dist: numpy~=2.2
Requires-Dist: packaging~=25.0
Requires-Dist: pandas~=2.2
Requires-Dist: plotly~=5.22
Dynamic: license-file
